Metadata-Version: 2.2
Name: kotok
Version: 1.0.0
Summary: Korean morphological analyzer based on the BERT architecture
Home-page: http://github.com/Daeun271/kotok
Author: Daeun Jung
Author-email: Daeun.Jung@ruhr-uni-bochum.de
Classifier: Programming Language :: Python :: 3
Classifier: License :: OSI Approved :: GNU General Public License v3 (GPLv3)
Classifier: Operating System :: OS Independent
Requires-Python: >=3.12
License-File: LICENSE
Requires-Dist: transformers>=4.48.0
Requires-Dist: torch>=2.6.0
Requires-Dist: accelerate>=1.3.0
Requires-Dist: tensorboard>=2.18.0
Requires-Dist: kiwipiepy>=0.20.0
Requires-Dist: tqdm>=4.67.0
Requires-Dist: requests>=2.32.0
Dynamic: author
Dynamic: author-email
Dynamic: classifier
Dynamic: description
Dynamic: description-content-type
Dynamic: home-page
Dynamic: requires-dist
Dynamic: requires-python
Dynamic: summary
